dexmetadata/__init__.py
dexmetadata/bytecode.py
dexmetadata/cache.py
dexmetadata/cli.py
dexmetadata/constants.py
dexmetadata/coverage.py
dexmetadata/decoder.py
dexmetadata/fetcher.py
dexmetadata/models.py
dexmetadata/optimize.py
dexmetadata/progress.py
dexmetadata/py.typed
dexmetadata/registry.py
dexmetadata/utils.py
dexmetadata/contracts/PoolMetadataFetcher.9e8b07e3.bin
dexmetadata/contracts/PoolMetadataFetcher.sol
dexmetadata/contracts/UniswapV4MetadataFetcher.a4301dbb.bin
dexmetadata/contracts/UniswapV4MetadataFetcher.sol
dexmetadata/handlers/__init__.py
dexmetadata/handlers/base.py
dexmetadata/handlers/default.py
dexmetadata/handlers/uniswap_v4.py
dexmetadata-0.1.8.dist-info/METADATA
dexmetadata-0.1.8.dist-info/WHEEL
dexmetadata-0.1.8.dist-info/entry_points.txt
dexmetadata-0.1.8.dist-info/licenses/LICENSE
dexmetadata-0.1.8.dist-info/RECORD
