Metadata-Version: 2.4
Name: dexmetadata
Version: 0.1.8
Summary: A deployless multicall library for fetching DEX pool metadata
Author-email: Yaser Martinez Palenzuela <yaser.martinez@gmail.com>
License-File: LICENSE
Requires-Python: >=3.10
Requires-Dist: diskcache>=5.6.3
Requires-Dist: eth-abi>=4.0.0
Requires-Dist: rich>=13.9.4
Requires-Dist: web3>=6.0.0
